Workbook

Sheet README
A1: Model Complexity & Integration Cost Matrix
A3: Purpose | B3: Show that integration cost often dominates model choice.
A4: Core idea | B4: Architecture risk is driven by systems, workflows, controls, and accountability — not by model sophistication alone.
A5: How to use | B5: Review the three use cases, adjust warning flags, check driver weights, and use the architecture summary as an executive triage view.
A6: What it does NOT do | B6: It does not replace a full architecture assessment, compliance review, security review, or implementation estimate.
A7: Governance Terminology | B7: Fallback = predefined safe operational alternative path. Override = human authority to intervene or reverse an AI-supported action. Rollback = recovery of already applied operational changes.
A8: Important | B8: This file is a preliminary architecture filter. It surfaces escalation points that require deeper review before implementation.

Sheet Architecture Complexity
A1: Model Complexity & Integration Cost Matrix
A2: Purpose: Show that integration cost dominates model choice.
A3: Core idea: Architecture risk is driven by systems, not models.
A4: This sheet is an executive summary. Detailed warning flags and driver weights are reviewed on the following sheets.
A6: Parameter | B6: Use Case 1 | C6: Use Case 2 | D6: Use Case 3
A7: BUSINESS CASE DESCRIPTION
A8: Use Case Name | B8: Internal Meeting Summary Assistant | C8: Invoice Exception Detection Assistant | D8: Procurement Anomaly Review Assistant
A9: Business Goal | B9: Internal productivity support | C9: Finance review support | D9: Procurement review support
A10: Short Description | B10: Summarizes meetings, extracts action items, and prepares draft follow-up notes. | C10: Highlights invoice exceptions and unusual payment requests for finance review. | D10: Identifies unusual procurement patterns and prioritizes cases for contextual review.
A12: SOLUTION APPROACH
A13: AI Pattern | B13: Conversational / Recognition | C13: Patterns & Anomalies | D13: Patterns & Anomalies
A14: AI Mechanism / Tooling | B14: LLM | C14: Rules + LLM + RAG | D14: Rules + LLM + RAG
A15: Contextual Layer | B15: Meeting transcript / notes | C15: Payment request, invoice, contract, approval history | D15: Vendor history, pricing history, procurement category, approval context
A16: Operational Controls | B16: Human editing before distribution | C16: Human finance review + deterministic controls | D16: Human review + deterministic controls
A18: ARCHITECTURAL ASSESSMENT
A19: Cost Burden Index | B19: =IF(B22=0,0,SUMPRODUCT(--('Architecture Warnings'!B$5:B$18="YES"),(('Integration Cost Drivers'!$B$5:$B$18="LOW")*1+('Integration Cost Drivers'!$B$5:$B$18="MEDIUM")*2+('Integration Cost Drivers'!$B$5:$B$18="HIGH")*3))/B22) -> 0 | C19: =IF(C22=0,0,SUMPRODUCT(--('Architecture Warnings'!C$5:C$18="YES"),(('Integration Cost Drivers'!$B$5:$B$18="LOW")*1+('Integration Cost Drivers'!$B$5:$B$18="MEDIUM")*2+('Integration Cost Drivers'!$B$5:$B$18="HIGH")*3))/C22) -> 2.4 | D19: =IF(D22=0,0,SUMPRODUCT(--('Architecture Warnings'!D$5:D$18="YES"),(('Integration Cost Drivers'!$B$5:$B$18="LOW")*1+('Integration Cost Drivers'!$B$5:$B$18="MEDIUM")*2+('Integration Cost Drivers'!$B$5:$B$18="HIGH")*3))/D22) -> 2.5
A20: Complexity Burden Index | B20: =IF(B22=0,0,SUMPRODUCT(--('Architecture Warnings'!B$5:B$18="YES"),(('Integration Cost Drivers'!$C$5:$C$18="LOW")*1+('Integration Cost Drivers'!$C$5:$C$18="MEDIUM")*2+('Integration Cost Drivers'!$C$5:$C$18="HIGH")*3))/B22) -> 0 | C20: =IF(C22=0,0,SUMPRODUCT(--('Architecture Warnings'!C$5:C$18="YES"),(('Integration Cost Drivers'!$C$5:$C$18="LOW")*1+('Integration Cost Drivers'!$C$5:$C$18="MEDIUM")*2+('Integration Cost Drivers'!$C$5:$C$18="HIGH")*3))/C22) -> 2.4 | D20: =IF(D22=0,0,SUMPRODUCT(--('Architecture Warnings'!D$5:D$18="YES"),(('Integration Cost Drivers'!$C$5:$C$18="LOW")*1+('Integration Cost Drivers'!$C$5:$C$18="MEDIUM")*2+('Integration Cost Drivers'!$C$5:$C$18="HIGH")*3))/D22) -> 2.5
A21: Failure Risk Index | B21: =IF(B22=0,0,SUMPRODUCT(--('Architecture Warnings'!B$5:B$18="YES"),(('Integration Cost Drivers'!$D$5:$D$18="LOW")*1+('Integration Cost Drivers'!$D$5:$D$18="MEDIUM")*2+('Integration Cost Drivers'!$D$5:$D$18="HIGH")*3))/B22) -> 0 | C21: =IF(C22=0,0,SUMPRODUCT(--('Architecture Warnings'!C$5:C$18="YES"),(('Integration Cost Drivers'!$D$5:$D$18="LOW")*1+('Integration Cost Drivers'!$D$5:$D$18="MEDIUM")*2+('Integration Cost Drivers'!$D$5:$D$18="HIGH")*3))/C22) -> 2.2 | D21: =IF(D22=0,0,SUMPRODUCT(--('Architecture Warnings'!D$5:D$18="YES"),(('Integration Cost Drivers'!$D$5:$D$18="LOW")*1+('Integration Cost Drivers'!$D$5:$D$18="MEDIUM")*2+('Integration Cost Drivers'!$D$5:$D$18="HIGH")*3))/D22) -> 2.3333333
A22: Active Warning Count | B22: =COUNTIF('Architecture Warnings'!B5:B18,"YES") -> 0 | C22: =COUNTIF('Architecture Warnings'!C5:C18,"YES") -> 5 | D22: =COUNTIF('Architecture Warnings'!D5:D18,"YES") -> 6
A23: High Escalation Count | B23: =SUMPRODUCT(--('Architecture Warnings'!B5:B18="YES"),--('Architecture Warnings'!$E$5:$E$18="HIGH")) -> 0 | C23: =SUMPRODUCT(--('Architecture Warnings'!C5:C18="YES"),--('Architecture Warnings'!$E$5:$E$18="HIGH")) -> 2 | D23: =SUMPRODUCT(--('Architecture Warnings'!D5:D18="YES"),--('Architecture Warnings'!$E$5:$E$18="HIGH")) -> 3
A24: Architecture Complexity Level | B24: =IF(B22=0,"LOW",IF(AVERAGE(B19:B21)<1.5,"LOW",IF(AVERAGE(B19:B21)<=2.5,"MEDIUM","HIGH"))) -> LOW | C24: =IF(C22=0,"LOW",IF(AVERAGE(C19:C21)<1.5,"LOW",IF(AVERAGE(C19:C21)<=2.5,"MEDIUM","HIGH"))) -> MEDIUM | D24: =IF(D22=0,"LOW",IF(AVERAGE(D19:D21)<1.5,"LOW",IF(AVERAGE(D19:D21)<=2.5,"MEDIUM","HIGH"))) -> MEDIUM
A26: EXECUTIVE REVIEW NOTES
A27: Recommended Architecture | B27: Standalone Assist Workflow | C27: Human Review + Deterministic Controls | D27: Human Review + Retrieval Layer
A28: Executive Attention Required | B28: =IF(AND('Architecture Warnings'!B5="YES",'Architecture Warnings'!$E5="HIGH"),'Architecture Warnings'!$A5&"; ","")&IF(AND('Architecture Warnings'!B6="YES",'Architecture Warnings'!$E6="HIGH"),'Architecture Warnings'!$A6&"; ","")&IF(AND('Architecture Warnings'!B7="YES",'Architecture Warnings'!$E7="HIGH"),'Architecture Warnings'!$A7&"; ","")&IF(AND('Architecture Warnings'!B8="YES",'Architecture Warnings'!$E8="HIGH"),'Architecture Warnings'!$A8&"; ","")&IF(AND('Architecture Warnings'!B9="YES",'Architecture Warnings'!$E9="HIGH"),'Architecture Warnings'!$A9&"; ","")&IF(AND('Architecture Warnings'!B10="YES",'Architecture Warnings'!$E10="HIGH"),'Architecture Warnings'!$A10&"; ","")&IF(AND('Architecture Warnings'!B11="YES",'Architecture Warnings'!$E11="HIGH"),'Architecture Warnings'!$A11&"; ","")&IF(AND('Architecture Warnings'!B12="YES",'Architecture Warnings'!$E12="HIGH"),'Architecture Warnings'!$A12&"; ","")&IF(AND('Architecture Warnings'!B13="YES",'Architecture Warnings'!$E13="HIGH"),'Architecture Warnings'!$A13&"; ","")&IF(AND('Architecture Warnings'!B14="YES",'Architecture Warnings'!$E14="HIGH"),'Architecture Warnings'!$A14&"; ","")&IF(AND('Architecture Warnings'!B15="YES",'Architecture Warnings'!$E15="HIGH"),'Architecture Warnings'!$A15&"; ","")&IF(AND('Architecture Warnings'!B16="YES",'Architecture Warnings'!$E16="HIGH"),'Architecture Warnings'!$A16&"; ","") | C28: =IF(AND('Architecture Warnings'!C5="YES",'Architecture Warnings'!$E5="HIGH"),'Architecture Warnings'!$A5&"; ","")&IF(AND('Architecture Warnings'!C6="YES",'Architecture Warnings'!$E6="HIGH"),'Architecture Warnings'!$A6&"; ","")&IF(AND('Architecture Warnings'!C7="YES",'Architecture Warnings'!$E7="HIGH"),'Architecture Warnings'!$A7&"; ","")&IF(AND('Architecture Warnings'!C8="YES",'Architecture Warnings'!$E8="HIGH"),'Architecture Warnings'!$A8&"; ","")&IF(AND('Architecture Warnings'!C9="YES",'Architecture Warnings'!$E9="HIGH"),'Architecture Warnings'!$A9&"; ","")&IF(AND('Architecture Warnings'!C10="YES",'Architecture Warnings'!$E10="HIGH"),'Architecture Warnings'!$A10&"; ","")&IF(AND('Architecture Warnings'!C11="YES",'Architecture Warnings'!$E11="HIGH"),'Architecture Warnings'!$A11&"; ","")&IF(AND('Architecture Warnings'!C12="YES",'Architecture Warnings'!$E12="HIGH"),'Architecture Warnings'!$A12&"; ","")&IF(AND('Architecture Warnings'!C13="YES",'Architecture Warnings'!$E13="HIGH"),'Architecture Warnings'!$A13&"; ","")&IF(AND('Architecture Warnings'!C14="YES",'Architecture Warnings'!$E14="HIGH"),'Architecture Warnings'!$A14&"; ","")&IF(AND('Architecture Warnings'!C15="YES",'Architecture Warnings'!$E15="HIGH"),'Architecture Warnings'!$A15&"; ","")&IF(AND('Architecture Warnings'!C16="YES",'Architecture Warnings'!$E16="HIGH"),'Architecture Warnings'!$A16&"; ","") -> Audit trail incomplete; Workflow Synchronization required; | D28: =IF(AND('Architecture Warnings'!D5="YES",'Architecture Warnings'!$E5="HIGH"),'Architecture Warnings'!$A5&"; ","")&IF(AND('Architecture Warnings'!D6="YES",'Architecture Warnings'!$E6="HIGH"),'Architecture Warnings'!$A6&"; ","")&IF(AND('Architecture Warnings'!D7="YES",'Architecture Warnings'!$E7="HIGH"),'Architecture Warnings'!$A7&"; ","")&IF(AND('Architecture Warnings'!D8="YES",'Architecture Warnings'!$E8="HIGH"),'Architecture Warnings'!$A8&"; ","")&IF(AND('Architecture Warnings'!D9="YES",'Architecture Warnings'!$E9="HIGH"),'Architecture Warnings'!$A9&"; ","")&IF(AND('Architecture Warnings'!D10="YES",'Architecture Warnings'!$E10="HIGH"),'Architecture Warnings'!$A10&"; ","")&IF(AND('Architecture Warnings'!D11="YES",'Architecture Warnings'!$E11="HIGH"),'Architecture Warnings'!$A11&"; ","")&IF(AND('Architecture Warnings'!D12="YES",'Architecture Warnings'!$E12="HIGH"),'Architecture Warnings'!$A12&"; ","")&IF(AND('Architecture Warnings'!D13="YES",'Architecture Warnings'!$E13="HIGH"),'Architecture Warnings'!$A13&"; ","")&IF(AND('Architecture Warnings'!D14="YES",'Architecture Warnings'!$E14="HIGH"),'Architecture Warnings'!$A14&"; ","")&IF(AND('Architecture Warnings'!D15="YES",'Architecture Warnings'!$E15="HIGH"),'Architecture Warnings'!$A15&"; ","")&IF(AND('Architecture Warnings'!D16="YES",'Architecture Warnings'!$E16="HIGH"),'Architecture Warnings'!$A16&"; ","") -> Audit trail incomplete; Workflow Synchronization required;
A29: Assessment Caveat | B29: =IF('Architecture Warnings'!B17="YES","PII / data residency flag raised — compliance validation required. ","")&IF('Architecture Warnings'!B18="YES","Decision traceability flag raised — audit-grade logging and retention validation required.","") | C29: =IF('Architecture Warnings'!C17="YES","PII / data residency flag raised — compliance validation required. ","")&IF('Architecture Warnings'!C18="YES","Decision traceability flag raised — audit-grade logging and retention validation required.","") | D29: =IF('Architecture Warnings'!D17="YES","PII / data residency flag raised — compliance validation required. ","")&IF('Architecture Warnings'!D18="YES","Decision traceability flag raised — audit-grade logging and retention validation required.","") -> Decision traceability flag raised — audit-grade logging and retention validation required.
A30: Recommended architecture patterns are illustrative and require solution-specific validation.
A32: Index Logic: | B32: LOW = 1
B33: MEDIUM = 2
B34: HIGH = 3
A36: Composite indices are calculated as simple averages across active architectural factors.

Sheet Integration Cost Drivers
A1: Integration Cost Drivers
A2: Purpose: Assign intrinsic burden weights to the same factors used on the Architecture Warnings sheet.
A4: Driver | B4: Cost Impact | C4: Complexity Impact | D4: Failure Risk | E4: Escalation Notes
A5: AI writes directly into core systems | B5: HIGH | C5: HIGH | D5: HIGH | E5: Direct write-back can materially increase implementation, testing, and recovery burden.
A6: Multi-system write access required | B6: HIGH | C6: HIGH | D6: HIGH | E6: Cross-system write orchestration can create transaction consistency and rollback complexity.
A7: No deterministic fallback | B7: MEDIUM | C7: MEDIUM | D7: HIGH | E7: Fallback design is essential where AI-supported workflows can fail or degrade.
A8: Human override unclear | B8: LOW | C8: MEDIUM | D8: MEDIUM | E8: Clarify who can intervene, reverse, or override AI-supported outputs.
A9: Audit trail incomplete | B9: MEDIUM | C9: MEDIUM | D9: MEDIUM | E9: Audit logging is required for review, troubleshooting, and accountability.
A10: Business rules hidden inside prompts | B10: LOW | C10: MEDIUM | D10: MEDIUM | E10: Rules should be externalized into testable policy or controls where practical.
A11: Context assembled from multiple systems | B11: HIGH | C11: HIGH | D11: MEDIUM | E11: Multi-source context raises mapping, consistency, and orchestration burden.
A12: No clear source of truth | B12: HIGH | C12: HIGH | D12: HIGH | E12: Unclear master data ownership can undermine decision reliability.
A13: Identity & Access required | B13: MEDIUM | C13: MEDIUM | D13: MEDIUM | E13: Access control is mature but still requires proper role and permission design.
A14: Workflow Synchronization required | B14: HIGH | C14: HIGH | D14: HIGH | E14: State handoffs and workflow synchronization can become major integration work.
A15: Monitoring required | B15: MEDIUM | C15: MEDIUM | D15: MEDIUM | E15: Monitoring adds operating discipline but is usually manageable with existing tooling.
... A18: Decision Traceability Storage | B18: HIGH | C18: HIGH | D18: HIGH | E18: Traceability flag raised: audit-grade logging, encrypted retention, retrieval, and evidence preservation review required.

Sheet Architecture Warnings
A1: Architecture Warning Signs
A2: Purpose: Identify hidden architecture escalation points before implementation.
A4: Warning Sign | B4: Use Case 1 | C4: Use Case 2 | D4: Use Case 3 | E4: Escalation Level | F4: Architecture Attention Required
A5: AI writes directly into core systems | B5: NO | C5: NO | D5: NO | E5: HIGH | F5: Deterministic fallback and approval controls required.
A6: Multi-system write access required | B6: NO | C6: NO | D6: NO | E6: HIGH | F6: Integration dependency mapping required.
A7: No deterministic fallback | B7: NO | C7: NO | D7: NO | E7: HIGH | F7: Safe alternative operating path required.
A8: Human override unclear | B8: NO | C8: NO | D8: NO | E8: MEDIUM | F8: Decision ownership and intervention authority must be clarified.
A9: Audit trail incomplete | B9: NO | C9: YES | D9: YES | E9: HIGH | F9: Compliance logging review required.
A10: Business rules hidden inside prompts | B10: NO | C10: NO | D10: NO | E10: MEDIUM | F10: Explicit policy / rules layer recommended.
A11: Context assembled from multiple systems | B11: NO | C11: YES | D11: YES | E11: MEDIUM | F11: Context orchestration review required.
A12: No clear source of truth | B12: NO | C12: NO | D12: NO | E12: HIGH | F12: Master data alignment required.
A13: Identity & Access required | B13: NO | C13: YES | D13: YES | E13: MEDIUM | F13: Access model, roles, and permissions review required.
A14: Workflow Synchronization required | B14: NO | C14: YES | D14: YES | E14: HIGH | F14: Workflow handoff and state synchronization review required.
A15: Monitoring required | B15: NO | C15: YES | D15: YES | E15: MEDIUM | F15: Monitoring metrics and escalation triggers required.
... A18: Decision traceability required but not architected | B18: NO | C18: NO | D18: YES | E18: HIGH | F18: Audit-grade logging architecture required.
A20: Escalation Level Logic: | B20: HIGH indicates a warning that may materially change architecture cost, governance posture, or operational liability.
B21: MEDIUM indicates a relevant architecture concern that usually requires review but does not automatically change executive risk posture.
